wtfork/__init__.py
wtfork/main.py
wtfork-1.0.2.dist-info/METADATA
wtfork-1.0.2.dist-info/WHEEL
wtfork-1.0.2.dist-info/entry_points.txt
wtfork-1.0.2.dist-info/top_level.txt
wtfork-1.0.2.dist-info/RECORD
