Metadata-Version: 2.4
Name: WTFork
Version: 1.0.2
Summary: Detects invisible network exploits in GitHub Actions pins
Author: Javier Dominguez
Project-URL: Homepage, https://github.com/javixeneize/wtfork
Classifier: Programming Language :: Python :: 3
Classifier: License :: OSI Approved :: MIT License
Classifier: Operating System :: OS Independent
Requires-Python: >=3.7
Requires-Dist: requests
